pybasekit/__init__.py
pybasekit-1.0.2.dist-info/LICENSE
pybasekit-1.0.2.dist-info/METADATA
pybasekit-1.0.2.dist-info/WHEEL
pybasekit-1.0.2.dist-info/top_level.txt
pybasekit-1.0.2.dist-info/RECORD
