Metadata-Version: 2.1
Name: pybasekit
Version: 1.0.2
Summary: Basic local database system
Author: Because
Author-email: 
Keywords: python,db,database,storage
Classifier: Development Status :: 1 - Planning
Classifier: Intended Audience :: Developers
Classifier: Programming Language :: Python :: 3
Classifier: Operating System :: Microsoft :: Windows
License-File: LICENSE
